Workbook
Name aporte: ferramenta!$D$17
Name patrimonio: ferramenta!$D$20
Name qtd_anos: ferramenta!$D$18
Name rendimento_carteira: ferramenta!$D$13
Name salario: ferramenta!$D$12
Name sugestao_investimento: ferramenta!$D$14
Name taxa_mensal: ferramenta!$D$19

Sheet ferramenta
B11: CONFIGURAÇÕES
B12: Salário | D12: 5500
B13: Rendimento carteira | D13: 0.008
B14: Sugestão de investimento (30%) | D14: =D12*30% -> 1650
B16: INVESTIMENTO MENSAL
B17: Quanto investir por mês? | D17: 500
B18: Por quantos anos? | D18: 5
B19: Taxa de rendimento mensal? | D19: 0.01079
B20: Qual o patrimônio acumulado terei? | D20: =FV(taxa_mensal,qtd_anos*12,aporte*-1) -> 41888.457
B21: Quanto receberei de dividendo mensal? | D21: =patrimonio*rendimento_carteira -> 335.10766
B23: CENÁRIO | D23: Dividendo
A24: 2 | B24: Quanto terá em 2 anos? | C24: =FV(taxa_mensal,$A24*12,aporte*-1) -> 13613.814 | D24: =C24*rendimento_carteira -> 108.91051
A25: 5 | B25: Quanto terá em 5 anos? | C25: =FV(taxa_mensal,$A25*12,aporte*-1) -> 41888.457 | D25: =C25*rendimento_carteira -> 335.10766
A26: 10 | B26: Quanto terá em 10 anos? | C26: =FV(taxa_mensal,$A26*12,aporte*-1) -> 121642.11 | D26: =C26*rendimento_carteira -> 973.13685
A27: 20 | B27: Quanto terá em 20 anos? | C27: =FV(taxa_mensal,$A27*12,aporte*-1) -> 562599.2 | D27: =C27*rendimento_carteira -> 4500.7936
A28: 30 | B28: Quanto terá em 30 anos? | C28: =FV(taxa_mensal,$A28*12,aporte*-1) -> 2161084.8 | D28: =C28*rendimento_carteira -> 17288.679
B30: PERFIL | C30: agressivo
B31: Valor a ser investido por mês | C31: 1650
B33: TIPO DE FII | C33: Percentual sugerido | D33: Valores
B34: Papel | C34: =VLOOKUP($C$30&"-"&B34,'tab. apoio'!$A:$D,4,FALSE) -> 0.5 | D34: =$C$31*C34 -> 825
B35: Tijolo | C35: =VLOOKUP($C$30&"-"&B35,'tab. apoio'!$A:$D,4,FALSE) -> 0.1 | D35: =$C$31*C35 -> 165
B36: Híbridos | C36: =VLOOKUP($C$30&"-"&B36,'tab. apoio'!$A:$D,4,FALSE) -> 0.05 | D36: =$C$31*C36 -> 82.5
B37: FOFs | C37: =VLOOKUP($C$30&"-"&B37,'tab. apoio'!$A:$D,4,FALSE) -> 0.05 | D37: =$C$31*C37 -> 82.5
B38: Desenvolvimento | C38: =VLOOKUP($C$30&"-"&B38,'tab. apoio'!$A:$D,4,FALSE) -> 0.2 | D38: =$C$31*C38 -> 330
B39: Hotelaria | C39: =VLOOKUP($C$30&"-"&B39,'tab. apoio'!$A:$D,4,FALSE) -> 0.1 | D39: =$C$31*C39 -> 165
D40: =SUM(D34:D39) -> 1650

Sheet tab. apoio
B5: perfil | C5: TIPO DE FII | D5: %
A6: =$B$6&"-"&C6 -> Conservador-Papel | B6: Conservador | C6: Papel | D6: 0.3
A7: =$B$6&"-"&C7 -> Conservador-Tijolo | B7: Conservador | C7: Tijolo | D7: 0.5
A8: =$B$6&"-"&C8 -> Conservador-Híbridos | B8: Conservador | C8: Híbridos | D8: 0.1 | H8: Moderado-Tijolo | I8: =VLOOKUP(H8,$A:$D,4,FALSE) -> 0.4
A9: =$B$6&"-"&C9 -> Conservador-FOFs | B9: Conservador | C9: FOFs | D9: 0.1
A10: =$B$6&"-"&C10 -> Conservador-Desenvolvimento | B10: Conservador | C10: Desenvolvimento | D10: 0
A11: =$B$6&"-"&C11 -> Conservador-Hotelaria | B11: Conservador | C11: Hotelaria | D11: 0
A12: =B12&"-"&C12 -> Moderado-Papel | B12: Moderado | C12: Papel | D12: 0.32
A13: =B13&"-"&C13 -> Moderado-Tijolo | B13: Moderado | C13: Tijolo | D13: 0.4
A14: =B14&"-"&C14 -> Moderado-Híbridos | B14: Moderado | C14: Híbridos | D14: 0.08
A15: =B15&"-"&C15 -> Moderado-FOFs | B15: Moderado | C15: FOFs | D15: 0.1
A16: =B16&"-"&C16 -> Moderado-Desenvolvimento | B16: Moderado | C16: Desenvolvimento | D16: 0.05
A17: =B17&"-"&C17 -> Moderado-Hotelaria | B17: Moderado | C17: Hotelaria | D17: 0.05
A18: =$B$18&"-"&C18 -> Agressivo-Papel | B18: Agressivo | C18: Papel | D18: 0.5
A19: =$B$18&"-"&C19 -> Agressivo-Tijolo | B19: Agressivo | C19: Tijolo | D19: 0.1
A20: =$B$18&"-"&C20 -> Agressivo-Híbridos | B20: Agressivo | C20: Híbridos | D20: 0.05
A21: =$B$18&"-"&C21 -> Agressivo-FOFs | B21: Agressivo | C21: FOFs | D21: 0.05
A22: =$B$18&"-"&C22 -> Agressivo-Desenvolvimento | B22: Agressivo | C22: Desenvolvimento | D22: 0.2
A23: =$B$18&"-"&C23 -> Agressivo-Hotelaria | B23: Agressivo | C23: Hotelaria | D23: 0.1
